ambition_permissions/__init__.py
ambition_permissions/apps.py
ambition_permissions/group_names.py
ambition_permissions/groups_updater.py
ambition_permissions/urls.py
ambition_permissions/codenames/__init__.py
ambition_permissions/codenames/ae_review.py
ambition_permissions/codenames/auditor.py
ambition_permissions/codenames/clinic.py
ambition_permissions/codenames/lab.py
ambition_permissions/codenames/pii.py
ambition_permissions/codenames/pii_view.py
ambition_permissions/codenames/rando.py
ambition_permissions/codenames/tmg.py
ambition_permissions/management/__init__.py
ambition_permissions/management/commands/__init__.py
ambition_permissions/management/commands/update_edc_permissions.py
ambition_permissions/tests/__init__.py
ambition_permissions/tests/test_permissions.py
ambition_permissions/tests/urls.py
ambition_permissions/updaters/__init__.py
ambition_permissions/updaters/ae_review.py
ambition_permissions/updaters/auditor.py
ambition_permissions/updaters/clinic.py
ambition_permissions/updaters/lab.py
ambition_permissions/updaters/pii_models.py
ambition_permissions/updaters/rando.py
ambition_permissions/updaters/tmg.py
ambition_permissions/updaters/update_permissions.py
ambition_permissions-0.1.28.dist-info/AUTHORS
ambition_permissions-0.1.28.dist-info/LICENSE
ambition_permissions-0.1.28.dist-info/METADATA
ambition_permissions-0.1.28.dist-info/WHEEL
ambition_permissions-0.1.28.dist-info/top_level.txt
ambition_permissions-0.1.28.dist-info/RECORD
